{
    "/js/app.js": "/js/app.js",
    "/css/app.css": "/css/app.css",
    "/js/manifest.js": "/js/manifest.js",
    "/js/prefetch.js": "/js/prefetch.js",
    "/js/vendor.js": "/js/vendor.js",
    "/js/app.fd92ec7cc6e15c62b283.hot-update.js": "/js/app.fd92ec7cc6e15c62b283.hot-update.js",
    "/js/app.1e19f84266703dc7843f.hot-update.js": "/js/app.1e19f84266703dc7843f.hot-update.js",
    "/js/app.7470eef736e209299f49.hot-update.js": "/js/app.7470eef736e209299f49.hot-update.js",
    "/js/app.6de2bf10af06163c6db6.hot-update.js": "/js/app.6de2bf10af06163c6db6.hot-update.js",
    "/js/app.2c269ae1b7264aab795e.hot-update.js": "/js/app.2c269ae1b7264aab795e.hot-update.js",
    "/js/app.90c03867912793a04361.hot-update.js": "/js/app.90c03867912793a04361.hot-update.js",
    "/js/app.41ce0d0e9a48f752be2d.hot-update.js": "/js/app.41ce0d0e9a48f752be2d.hot-update.js",
    "/js/app.e9e66075463349ea9a9f.hot-update.js": "/js/app.e9e66075463349ea9a9f.hot-update.js",
    "/js/app.551d0735a1316e001c30.hot-update.js": "/js/app.551d0735a1316e001c30.hot-update.js",
    "/js/app.136bb31a1f3e552849fa.hot-update.js": "/js/app.136bb31a1f3e552849fa.hot-update.js",
    "/js/app.dd905fc16ce719f6c84f.hot-update.js": "/js/app.dd905fc16ce719f6c84f.hot-update.js",
    "/js/app.d48263e83c210a4f745b.hot-update.js": "/js/app.d48263e83c210a4f745b.hot-update.js",
    "/js/app.67cae25f0c810292a5ac.hot-update.js": "/js/app.67cae25f0c810292a5ac.hot-update.js",
    "/js/app.99e7ae1592765c0d2d8c.hot-update.js": "/js/app.99e7ae1592765c0d2d8c.hot-update.js"
}
