{
    "/js/app.js": "/js/app.js",
    "/css/app.css": "/css/app.css",
    "/js/manifest.js": "/js/manifest.js",
    "/js/prefetch.js": "/js/prefetch.js",
    "/js/vendor.js": "/js/vendor.js",
    "/js/app.0133c1604b7c8ec18218.hot-update.js": "/js/app.0133c1604b7c8ec18218.hot-update.js",
    "/js/app.7f4cea677b73d533b494.hot-update.js": "/js/app.7f4cea677b73d533b494.hot-update.js",
    "/js/app.80cdf27c8f1341614274.hot-update.js": "/js/app.80cdf27c8f1341614274.hot-update.js",
    "/js/app.98ab3e8075f17cc6f882.hot-update.js": "/js/app.98ab3e8075f17cc6f882.hot-update.js",
    "/js/app.1d77328e249d93b74b43.hot-update.js": "/js/app.1d77328e249d93b74b43.hot-update.js",
    "/js/app.23bc2d4e2e12d97ee101.hot-update.js": "/js/app.23bc2d4e2e12d97ee101.hot-update.js",
    "/js/app.14481f839823d6fdfa31.hot-update.js": "/js/app.14481f839823d6fdfa31.hot-update.js",
    "/js/app.4dce5d7437d7c1fbc438.hot-update.js": "/js/app.4dce5d7437d7c1fbc438.hot-update.js",
    "/js/app.e161e32d47ab46c701e9.hot-update.js": "/js/app.e161e32d47ab46c701e9.hot-update.js",
    "/js/app.0955714953a148c9a3bb.hot-update.js": "/js/app.0955714953a148c9a3bb.hot-update.js",
    "/js/app.bcf7c6aee14450337bce.hot-update.js": "/js/app.bcf7c6aee14450337bce.hot-update.js",
    "/js/app.8aa0cff0d2640c712508.hot-update.js": "/js/app.8aa0cff0d2640c712508.hot-update.js",
    "/js/app.ffeb4ef6c38893659219.hot-update.js": "/js/app.ffeb4ef6c38893659219.hot-update.js",
    "/js/app.6b92161ed47fb56cb1f3.hot-update.js": "/js/app.6b92161ed47fb56cb1f3.hot-update.js",
    "/js/app.41aad15531cda0a20529.hot-update.js": "/js/app.41aad15531cda0a20529.hot-update.js",
    "/js/app.1a23ed75f71e4f6c3a2e.hot-update.js": "/js/app.1a23ed75f71e4f6c3a2e.hot-update.js"
}
